pdf_action_inspector/__init__.py
pdf_action_inspector/mcp_server.py
pdf_action_inspector/config/__init__.py
pdf_action_inspector/config/policies.py
pdf_action_inspector/config/settings.py
pdf_action_inspector/core/__init__.py
pdf_action_inspector/core/cache_manager.py
pdf_action_inspector/core/error_handler.py
pdf_action_inspector/core/inspector.py
pdf_action_inspector/utils/__init__.py
pdf_action_inspector/utils/action_extractor.py
pdf_action_inspector/utils/pdf_utils.py
pdf_action_inspector-0.1.1.dist-info/licenses/LICENSE
pdf_action_inspector-0.1.1.dist-info/METADATA
pdf_action_inspector-0.1.1.dist-info/WHEEL
pdf_action_inspector-0.1.1.dist-info/entry_points.txt
pdf_action_inspector-0.1.1.dist-info/top_level.txt
pdf_action_inspector-0.1.1.dist-info/RECORD
