Metadata-Version: 2.4
Name: pdf-action-inspector
Version: 0.1.1
Summary: A Model Context Protocol server for extracting and analyzing JavaScript Actions from PDF files
Author-email: "Foxit Software Inc." <security-ml@foxitsoftware.com>
License: MIT
Project-URL: Homepage, https://github.com/foxitsoftware/PDFActionInspector
Project-URL: Repository, https://github.com/foxitsoftware/PDFActionInspector
Project-URL: Issues, https://github.com/foxitsoftware/PDFActionInspector/issues
Project-URL: Documentation, https://github.com/foxitsoftware/PDFActionInspector#readme
Keywords: pdf,security,analysis,javascript,actions,mcp,model-context-protocol
Classifier: Development Status :: 4 - Beta
Classifier: Intended Audience :: Developers
Classifier: Intended Audience :: Information Technology
Classifier: Topic :: Security
Classifier: Topic :: Software Development :: Libraries :: Python Modules
Classifier: Topic :: Text Processing :: General
Classifier: License :: OSI Approved :: MIT License
Classifier: Programming Language :: Python :: 3
Classifier: Programming Language :: Python :: 3.10
Classifier: Programming Language :: Python :: 3.11
Classifier: Programming Language :: Python :: 3.12
Classifier: Programming Language :: Python :: 3.13
Classifier: Operating System :: OS Independent
Requires-Python: >=3.10
License-File: LICENSE
Requires-Dist: PyPDF2>=3.0.0
Requires-Dist: fastmcp>=2.0.0
Provides-Extra: dev
Requires-Dist: build>=0.8.0; extra == "dev"
Requires-Dist: pytest>=7.0.0; extra == "dev"
Requires-Dist: black>=22.0.0; extra == "dev"
Requires-Dist: flake8>=4.0.0; extra == "dev"
Requires-Dist: twine>=4.0.0; extra == "dev"
Dynamic: license-file
